integrify/__init__.py
integrify/api.py
integrify/logger.py
integrify/schemas.py
integrify/utils.py
integrify/azericard/__init__.py
integrify/azericard/client.py
integrify/azericard/env.py
integrify/azericard/handler.py
integrify/azericard/helpers.py
integrify/azericard/utils.py
integrify/azericard/schemas/__init__.py
integrify/azericard/schemas/callback.py
integrify/azericard/schemas/common.py
integrify/azericard/schemas/enums.py
integrify/azericard/schemas/response.py
integrify/azericard/schemas/request/__init__.py
integrify/azericard/schemas/request/auth.py
integrify/azericard/schemas/request/transfer.py
integrify/epoint/README.md
integrify/epoint/__init__.py
integrify/epoint/client.py
integrify/epoint/env.py
integrify/epoint/handlers.py
integrify/epoint/helpers.py
integrify/epoint/schemas/__init__.py
integrify/epoint/schemas/callback.py
integrify/epoint/schemas/enums.py
integrify/epoint/schemas/request.py
integrify/epoint/schemas/response.py
integrify/kapital/__init__.py
integrify/kapital/client.py
integrify/kapital/env.py
integrify/kapital/handlers.py
integrify/kapital/schemas/__init__.py
integrify/kapital/schemas/enums.py
integrify/kapital/schemas/request.py
integrify/kapital/schemas/utils.py
integrify/kapital/schemas/response/__init__.py
integrify/kapital/schemas/response/base_response.py
integrify/kapital/schemas/response/detailed_order_response.py
integrify/kapital/schemas/response/order_response.py
integrify/kapital/schemas/response/refund_response.py
integrify/kapital/schemas/response/token_response.py
integrify/lsim/__init__.py
integrify/lsim/env.py
integrify/lsim/types.py
integrify/lsim/bulk/__init__.py
integrify/lsim/bulk/client.py
integrify/lsim/bulk/env.py
integrify/lsim/bulk/handlers.py
integrify/lsim/bulk/schemas/__init__.py
integrify/lsim/bulk/schemas/enums.py
integrify/lsim/bulk/schemas/request.py
integrify/lsim/bulk/schemas/response.py
integrify/lsim/single/__init__.py
integrify/lsim/single/client.py
integrify/lsim/single/env.py
integrify-2.2.2.dist-info/METADATA
integrify-2.2.2.dist-info/WHEEL
integrify-2.2.2.dist-info/licenses/LICENSE
integrify-2.2.2.dist-info/RECORD
